pyspark/__init__.pyi
pyspark/_globals.pyi
pyspark/_typing.pyi
pyspark/accumulators.pyi
pyspark/broadcast.pyi
pyspark/cloudpickle.pyi
pyspark/conf.pyi
pyspark/context.pyi
pyspark/daemon.pyi
pyspark/files.pyi
pyspark/find_spark_home.pyi
pyspark/heapq3.pyi
pyspark/java_gateway.pyi
pyspark/join.pyi
pyspark/profiler.pyi
pyspark/py.typed
pyspark/rdd.pyi
pyspark/rddsampler.pyi
pyspark/resource.pyi
pyspark/resourceinformation.pyi
pyspark/resultiterable.pyi
pyspark/serializers.pyi
pyspark/shell.pyi
pyspark/shuffle.pyi
pyspark/statcounter.pyi
pyspark/status.pyi
pyspark/storagelevel.pyi
pyspark/taskcontext.pyi
pyspark/traceback_utils.pyi
pyspark/util.pyi
pyspark/version.pyi
pyspark/worker.pyi
pyspark/ml/__init__.pyi
pyspark/ml/_typing.py
pyspark/ml/_typing.pyi
pyspark/ml/base.pyi
pyspark/ml/classification.pyi
pyspark/ml/clustering.pyi
pyspark/ml/common.pyi
pyspark/ml/evaluation.pyi
pyspark/ml/feature.pyi
pyspark/ml/fpm.pyi
pyspark/ml/functions.pyi
pyspark/ml/image.pyi
pyspark/ml/pipeline.pyi
pyspark/ml/recommendation.pyi
pyspark/ml/regression.pyi
pyspark/ml/stat.pyi
pyspark/ml/tree.pyi
pyspark/ml/tuning.pyi
pyspark/ml/util.pyi
pyspark/ml/wrapper.pyi
pyspark/ml/linalg/__init__.pyi
pyspark/ml/param/__init__.pyi
pyspark/ml/param/_shared_params_code_gen.pyi
pyspark/ml/param/shared.pyi
pyspark/mllib/__init__.pyi
pyspark/mllib/_typing.pyi
pyspark/mllib/classification.pyi
pyspark/mllib/clustering.pyi
pyspark/mllib/common.pyi
pyspark/mllib/evaluation.pyi
pyspark/mllib/feature.pyi
pyspark/mllib/fpm.pyi
pyspark/mllib/random.pyi
pyspark/mllib/recommendation.pyi
pyspark/mllib/regression.pyi
pyspark/mllib/tree.pyi
pyspark/mllib/util.pyi
pyspark/mllib/linalg/__init__.pyi
pyspark/mllib/linalg/distributed.pyi
pyspark/mllib/stat/KernelDensity.pyi
pyspark/mllib/stat/__init__.pyi
pyspark/mllib/stat/_statistics.pyi
pyspark/mllib/stat/distribution.pyi
pyspark/mllib/stat/test.pyi
pyspark/sql/__init__.pyi
pyspark/sql/_typing.pyi
pyspark/sql/catalog.pyi
pyspark/sql/column.pyi
pyspark/sql/conf.pyi
pyspark_stubs-2.4.0.post12.dist-info/LICENSE
pyspark_stubs-2.4.0.post12.dist-info/METADATA
pyspark_stubs-2.4.0.post12.dist-info/WHEEL
pyspark_stubs-2.4.0.post12.dist-info/top_level.txt
pyspark_stubs-2.4.0.post12.dist-info/RECORD
