Metadata-Version: 2.1
Name: pyspark-stubs
Version: 2.4.0.post12
Summary: A collection of the Apache Spark stub files
Home-page: https://github.com/zero323/pyspark-stubs
Author: UNKNOWN
Author-email: UNKNOWN
License: UNKNOWN
Platform: UNKNOWN
Classifier: Programming Language :: Python :: 3 :: Only
Classifier: Development Status :: 4 - Beta
Classifier: License :: OSI Approved :: Apache Software License
Classifier: Intended Audience :: Developers
Classifier: Programming Language :: Python :: Implementation :: CPython
Classifier: Programming Language :: Python :: Implementation :: PyPy
Classifier: Typing :: Typed
Requires-Dist: pyspark (<3.0.0,>=2.4.0)
